<?xml version = '1.0' encoding = 'UTF-8'?>
<Diagram class="oracle.dbtools.crest.swingui.logical.DPVLogical" name="Logical" id="7E1E5ED3-F940-9857-C0CE-64E34404AA50">
<createdBy>JeffGeo</createdBy>
<modifiedBy>JeffGeo</modifiedBy>
<createdTime>2022-03-08 03:59:21 UTC</createdTime>
<autoRoute>false</autoRoute>
<boxInbox>true</boxInbox>
<showLegend>false</showLegend>
<showLabels>false</showLabels>
<showRelAttributes>false</showRelAttributes>
<gridEnabled>false</gridEnabled>
<showGrid>false</showGrid>
<diagramColor>-1</diagramColor>
<display>false</display>
<notation>1</notation>
<objectViews>
<OView class="oracle.dbtools.crest.swingui.logical.TVEntity" oid="11E56176-182D-E637-A75C-47594D6CE981" otype="Entity" vid="22ED15AD-ADBA-F5A1-3DB0-AB9FBE768E64">
<hideElementsInCurrentOnly>false</hideElementsInCurrentOnly>
<bounds x="140" y="415" width="170" height="110"/>
</OView>
<OView class="oracle.dbtools.crest.swingui.logical.TVEntity" oid="11F52DB5-559C-36FF-A996-16B2AF787449" otype="Entity" vid="11810D84-C051-A466-D842-208BD9C9740B">
<hideElementsInCurrentOnly>false</hideElementsInCurrentOnly>
<bounds x="637" y="594" width="170" height="110"/>
</OView>
<OView class="oracle.dbtools.crest.swingui.logical.TVEntity" oid="57D43D99-764F-6AAE-BEA6-2312817FE3AA" otype="Entity" vid="174BA541-4742-893A-0DAA-9E275E6B59B5">
<hideElementsInCurrentOnly>false</hideElementsInCurrentOnly>
<bounds x="893" y="302" width="170" height="110"/>
</OView>
<OView class="oracle.dbtools.crest.swingui.logical.TVEntity" oid="6D7C4E91-7FC0-D5E9-87DE-7E64C240303E" otype="Entity" vid="0AAAEDBB-90D4-57FD-608E-1EBD8B62D7A7">
<hideElementsInCurrentOnly>false</hideElementsInCurrentOnly>
<bounds x="107" y="129" width="170" height="110"/>
</OView>
<OView class="oracle.dbtools.crest.swingui.logical.TVEntity" oid="753DB6C1-ACDE-B061-727A-4518F4B72AFE" otype="Entity" vid="8D1BE85A-1521-F3C6-0033-C9534B3DF90B">
<hideElementsInCurrentOnly>false</hideElementsInCurrentOnly>
<bounds x="635" y="225" width="170" height="110"/>
</OView>
<OView class="oracle.dbtools.crest.swingui.logical.TVEntity" oid="7BB222A5-1134-BBE5-A040-A4B3F76E87A3" otype="Entity" vid="AB4CACA5-08D2-92A9-D257-49E499898623">
<hideElementsInCurrentOnly>false</hideElementsInCurrentOnly>
<bounds x="360" y="293" width="170" height="110"/>
</OView>
<OView class="oracle.dbtools.crest.swingui.logical.TVEntity" oid="CB5C3006-D9B5-DD6C-1D83-A774144BDBAE" otype="Entity" vid="10E226EE-B9BC-1C2E-E6B1-368FC31B692B">
<hideElementsInCurrentOnly>false</hideElementsInCurrentOnly>
<bounds x="617" y="20" width="170" height="110"/>
</OView>
<OView class="oracle.dbtools.crest.swingui.logical.TVEntity" oid="E412DE4C-2676-D776-5382-69BEBEA7A272" otype="Entity" vid="3F540BF5-7129-7527-2CE1-284463CDA2D2">
<hideElementsInCurrentOnly>false</hideElementsInCurrentOnly>
<bounds x="635" y="365" width="170" height="110"/>
</OView>
<OView class="oracle.dbtools.crest.swingui.logical.TVEntity" oid="EB6B0EE9-7DE5-EC38-A9D7-1B768C76160F" otype="Entity" vid="68E44A91-11C6-A29F-0213-E09E8EFC68F0">
<hideElementsInCurrentOnly>false</hideElementsInCurrentOnly>
<bounds x="1130" y="308" width="170" height="110"/>
</OView>
</objectViews>
<connectors>
<Connector class="oracle.dbtools.crest.swingui.logical.TVRelation" oid="077352A8-2587-2A07-A4F0-49B6CCA7F934" otype="Relation" vid_source="8D1BE85A-1521-F3C6-0033-C9534B3DF90B" vid_target="174BA541-4742-893A-0DAA-9E275E6B59B5">
<hideElementsInCurrentOnly>false</hideElementsInCurrentOnly>
<backgroundColor>-16777216</backgroundColor>
<lineWidth>1</lineWidth>
<points>
<point x="805" y="318"/>
<point x="893" y="318"/>
</points>
</Connector>
<Connector class="oracle.dbtools.crest.swingui.logical.TVRelation" oid="259555D8-A148-4F77-4A7D-06D8C8059A13" otype="Relation" vid_source="3F540BF5-7129-7527-2CE1-284463CDA2D2" vid_target="174BA541-4742-893A-0DAA-9E275E6B59B5">
<hideElementsInCurrentOnly>false</hideElementsInCurrentOnly>
<backgroundColor>-16777216</backgroundColor>
<lineWidth>1</lineWidth>
<points>
<point x="805" y="388"/>
<point x="893" y="388"/>
</points>
</Connector>
<Connector class="oracle.dbtools.crest.swingui.logical.TVRelation" oid="5886445C-210B-2163-7452-7C418FF244F4" otype="Relation" vid_source="0AAAEDBB-90D4-57FD-608E-1EBD8B62D7A7" vid_target="AB4CACA5-08D2-92A9-D257-49E499898623">
<hideElementsInCurrentOnly>false</hideElementsInCurrentOnly>
<backgroundColor>-16777216</backgroundColor>
<lineWidth>1</lineWidth>
<points>
<point x="276" y="239"/>
<point x="360" y="293"/>
</points>
</Connector>
<Connector class="oracle.dbtools.crest.swingui.logical.TVRelation" oid="807F2BDE-BAB4-4AB8-59BD-3341CB389D67" otype="Relation" vid_source="10E226EE-B9BC-1C2E-E6B1-368FC31B692B" vid_target="174BA541-4742-893A-0DAA-9E275E6B59B5">
<hideElementsInCurrentOnly>false</hideElementsInCurrentOnly>
<backgroundColor>-16777216</backgroundColor>
<lineWidth>1</lineWidth>
<points>
<point x="755" y="130"/>
<point x="924" y="302"/>
</points>
</Connector>
<Connector class="oracle.dbtools.crest.swingui.logical.TVRelation" oid="84AD581A-7E7A-FB67-FC45-F98C3CED4410" otype="Relation" vid_source="22ED15AD-ADBA-F5A1-3DB0-AB9FBE768E64" vid_target="AB4CACA5-08D2-92A9-D257-49E499898623">
<hideElementsInCurrentOnly>false</hideElementsInCurrentOnly>
<backgroundColor>-16777216</backgroundColor>
<lineWidth>1</lineWidth>
<points>
<point x="310" y="422"/>
<point x="360" y="395"/>
</points>
</Connector>
<Connector class="oracle.dbtools.crest.swingui.logical.TVRelation" oid="85FD1223-2E34-D6F0-E9DC-7EFE470C7A23" otype="Relation" vid_source="11810D84-C051-A466-D842-208BD9C9740B" vid_target="174BA541-4742-893A-0DAA-9E275E6B59B5">
<hideElementsInCurrentOnly>false</hideElementsInCurrentOnly>
<backgroundColor>-16777216</backgroundColor>
<lineWidth>1</lineWidth>
<points>
<point x="770" y="594"/>
<point x="929" y="412"/>
</points>
</Connector>
<Connector class="oracle.dbtools.crest.swingui.logical.TVRelation" oid="942C4F99-4920-AB40-D40A-CA29A034BBFA" otype="Relation" vid_source="8D1BE85A-1521-F3C6-0033-C9534B3DF90B" vid_target="AB4CACA5-08D2-92A9-D257-49E499898623">
<hideElementsInCurrentOnly>false</hideElementsInCurrentOnly>
<backgroundColor>-16777216</backgroundColor>
<lineWidth>1</lineWidth>
<points>
<point x="635" y="314"/>
<point x="530" y="314"/>
</points>
</Connector>
<Connector class="oracle.dbtools.crest.swingui.logical.TVRelation" oid="A72EF977-D280-696F-F09E-760550FB310D" otype="Relation" vid_source="68E44A91-11C6-A29F-0213-E09E8EFC68F0" vid_target="174BA541-4742-893A-0DAA-9E275E6B59B5">
<hideElementsInCurrentOnly>false</hideElementsInCurrentOnly>
<backgroundColor>-16777216</backgroundColor>
<lineWidth>1</lineWidth>
<points>
<point x="1130" y="360"/>
<point x="1063" y="360"/>
</points>
</Connector>
<Connector class="oracle.dbtools.crest.swingui.logical.TVRelation" oid="BBE34181-0EDE-4147-463B-467BF7F64BC7" otype="Relation" vid_source="3F540BF5-7129-7527-2CE1-284463CDA2D2" vid_target="AB4CACA5-08D2-92A9-D257-49E499898623">
<hideElementsInCurrentOnly>false</hideElementsInCurrentOnly>
<backgroundColor>-16777216</backgroundColor>
<lineWidth>1</lineWidth>
<points>
<point x="635" y="384"/>
<point x="530" y="384"/>
</points>
</Connector>
<Connector class="oracle.dbtools.crest.swingui.logical.TVRelation" oid="DFAB8130-7BF7-06BC-BD00-9B55022A22A4" otype="Relation" vid_source="10E226EE-B9BC-1C2E-E6B1-368FC31B692B" vid_target="AB4CACA5-08D2-92A9-D257-49E499898623">
<hideElementsInCurrentOnly>false</hideElementsInCurrentOnly>
<backgroundColor>-16777216</backgroundColor>
<lineWidth>1</lineWidth>
<points>
<point x="650" y="130"/>
<point x="496" y="293"/>
</points>
</Connector>
<Connector class="oracle.dbtools.crest.swingui.logical.TVRelation" oid="F03CC20D-02CC-5C12-062C-12BEDF1B4D53" otype="Relation" vid_source="11810D84-C051-A466-D842-208BD9C9740B" vid_target="AB4CACA5-08D2-92A9-D257-49E499898623">
<hideElementsInCurrentOnly>false</hideElementsInCurrentOnly>
<backgroundColor>-16777216</backgroundColor>
<lineWidth>1</lineWidth>
<points>
<point x="671" y="594"/>
<point x="495" y="403"/>
</points>
</Connector>
</connectors>
</Diagram>